{
"bodypres": [
"Bob Bizzo",
"Grant Burgoyne"
],
"seniorpres": [
"Marlene Cannova"
],
"outstanding": [
"Dave Riley",
"Rosalia Guillen"
],
"valedictorian": [
"Debra Colombana"
],
"salutatorian": [
"Mike Peters"
],
"english": [
"Linda Passetti"
],
"history": [
"Janie Layton"
],
"math": [
"Jeff Harris"
],
"science": [
"Doug Napp"
],
"art": [
"Janet Plant"
],
"drama": [
"Roseanne Regal"
],
"music": [
"Robin Crawford"
],
"worldlang": [
"Alicia Martinez"
],
"boyspe": [
"Jim Swanson"
],
"girlspe": [
"None"
],
"business": [
"Marry Ann Simmons"
],
"industrial": [
"Julius Norman"
],
"economics": [
"Jackie Ketchum"
],
"service": [
"Marlene Cannova",
"Robert Bizzo"
]
}