{
"bodypres": [
"Bryan Clark"
],
"seniorpres": [
"Steve Block"
],
"outstanding": [
"Ray Schnapp",
"Amy Hall"
],
"valedictorian": [
"Dave Sausjord"
],
"salutatorian": [
"Amy Hall"
],
"english": [
"David Lonich"
],
"history": [
"Maureen Murray"
],
"math": [
"Eric Bogatin"
],
"science": [
"Eric Bogatin"
],
"art": [
"Janet Smigelsky"
],
"drama": [
"Sandra Hansen",
"Peter Seagrave"
],
"music": [
"Sheryl Riley"
],
"worldlang": [
"None"
],
"boyspe": [
"Dave Taxier"
],
"girlspe": [
"None"
],
"business": [
"Donna Smith"
],
"industrial": [
"Ray Schnapp"
],
"economics": [
"Dana Delmas"
],
"service": [
"Carol Edwards",
"Maureen Murray"
]
}