{
"bodypres": [
"Lisa Maurino"
],
"seniorpres": [
"De Mary Dominguez"
],
"outstanding": [
"Lisa Maurino"
],
"valedictorian": [
"Lori Cheyne",
"Mike Semenoff"
],
"salutatorian": [
"Claudia Pratt"
],
"english": [
"Michele Santoro",
"Claudia Pratt"
],
"history": [
"Lisa Maurino"
],
"math": [
"Arnie Polster"
],
"science": [
"Laura Burgess",
"Jeana Colabianchi"
],
"art": [
"None"
],
"drama": [
"Steve Power",
"Cheryl Fluehr"
],
"music": [
"Steve Stanely"
],
"worldlang": [
"De Mary Dominguez",
"Claudia Pratt"
],
"boyspe": [
"None"
],
"girlspe": [
"Barbara Stockman"
],
"business": [
"Teresa Brand"
],
"industrial": [
"Paul Cologna"
],
"economics": [
"None"
],
"service": [
"De Mary Dominguez"
]
}